skinport/__init__.py
skinport/core.py
skinport-0.1.2.dist-info/LICENSE
skinport-0.1.2.dist-info/METADATA
skinport-0.1.2.dist-info/WHEEL
skinport-0.1.2.dist-info/top_level.txt
skinport-0.1.2.dist-info/RECORD
