Metadata-Version: 2.1
Name: skinport
Version: 0.1.2
Summary: A Python wrapper around the Skinport API.
Home-page: https://github.com/barnumbirr/skinport
Download-URL: https://github.com/barnumbirr/skinport/archive/refs/heads/master.zip
Author: Martin Simon
Author-email: me@martinsimon.me
License: UNKNOWN
Keywords: skinport,Counter Strike,CSGO,DOTA2,Rust,Team Fortress 2,TF2,wrapper,api
Platform: UNKNOWN
Classifier: Development Status :: 5 - Production/Stable
Classifier: Intended Audience :: Developers
Classifier: Operating System :: OS Independent
Classifier: Programming Language :: Python :: 3
Classifier: Programming Language :: Python :: 3.9
Classifier: Programming Language :: Python :: 3.10
Classifier: Topic :: Utilities
License-File: LICENSE
Requires-Dist: requests
